odoo/addons/analytic_operating_unit/README.rst
odoo/addons/analytic_operating_unit/__init__.py
odoo/addons/analytic_operating_unit/__manifest__.py
odoo/addons/analytic_operating_unit/models/__init__.py
odoo/addons/analytic_operating_unit/models/account_analytic_account.py
odoo/addons/analytic_operating_unit/security/analytic_account_security.xml
odoo/addons/analytic_operating_unit/static/description/icon.png
odoo/addons/analytic_operating_unit/views/analytic_account_view.xml
odoo11_addon_analytic_operating_unit-11.0.1.0.0.dist-info/DESCRIPTION.rst
odoo11_addon_analytic_operating_unit-11.0.1.0.0.dist-info/METADATA
odoo11_addon_analytic_operating_unit-11.0.1.0.0.dist-info/RECORD
odoo11_addon_analytic_operating_unit-11.0.1.0.0.dist-info/WHEEL
odoo11_addon_analytic_operating_unit-11.0.1.0.0.dist-info/metadata.json
odoo11_addon_analytic_operating_unit-11.0.1.0.0.dist-info/top_level.txt
